README.md
setup.py
fgp/VERSION.txt
fgp/__init__.py
fgp.egg-info/PKG-INFO
fgp.egg-info/SOURCES.txt
fgp.egg-info/dependency_links.txt
fgp.egg-info/entry_points.txt
fgp.egg-info/requires.txt
fgp.egg-info/top_level.txt
fgp/cli/__init__.py
fgp/cli/common.py
fgp/cli/extension/__init__.py
fgp/cli/extension/commands.py
fgp/cli/relation/__init__.py
fgp/cli/relation/commands.py
fgp/cli/store/__init__.py
fgp/cli/store/commands.py
fgp/controller/__init__.py
fgp/controller/applications.py
fgp/controller/client.py
fgp/controller/device.py
fgp/controller/event.py
fgp/controller/extension.py
fgp/controller/lambdas.py
fgp/controller/module.py
fgp/controller/reference.py
fgp/controller/relation.py
fgp/controller/store.py
fgp/model/__init__.py
fgp/model/application.py
fgp/model/device.py
fgp/model/fgp_session.py
fgp/model/meter.py
fgp/model/model.py
fgp/model/module.py
fgp/model/module_event.py
fgp/model/module_state.py
fgp/model/reference.py
fgp/model/transformer.py
fgp/utils/__init__.py
fgp/utils/datetime_to_ms.py