Metadata-Version: 2.1
Name: fgp
Version: 0.2.10
Summary: Future Grid API client
Home-page: https://gitlab.com/future-grid/fgp-api-python
Author: Future Grid
Author-email: team@future-grid.com
License: UNKNOWN
Platform: UNKNOWN
Classifier: Programming Language :: Python :: 3
Classifier: License :: OSI Approved :: MIT License
Classifier: Operating System :: OS Independent
